MANIFEST.in
README.rst
setup.cfg
setup.py
palal/__init__.py
palal/palal.py
palal.egg-info/PKG-INFO
palal.egg-info/SOURCES.txt
palal.egg-info/dependency_links.txt
palal.egg-info/entry_points.txt
palal.egg-info/requires.txt
palal.egg-info/top_level.txt
palal/_data/rules.yml
palal/_licenses/agpl-3.0.txt
palal/_licenses/apache-2.0.txt
palal/_licenses/artistic-2.0.txt
palal/_licenses/bsd-2-clause.txt
palal/_licenses/bsd-3-clause.txt
palal/_licenses/cc0.txt
palal/_licenses/epl-1.0.txt
palal/_licenses/gpl-2.0.txt
palal/_licenses/gpl-3.0.txt
palal/_licenses/isc.txt
palal/_licenses/lgpl-2.1.txt
palal/_licenses/lgpl-3.0.txt
palal/_licenses/mit.txt
palal/_licenses/mpl-2.0.txt
palal/_licenses/no-license.txt
palal/_licenses/unlicense.txt