Metadata-Version: 1.1
Name: palal
Version: 0.1.3
Summary: Pick a license, any license.
Home-page: https://github.com/alixedi/palal
Author: Ali Zaidi
Author-email: alixedi@gmail.com
License: MIT
Keywords: FOSS OSI license development
Platform: UNKNOWN
Classifier: Development Status :: 3 - Alpha
Classifier: Intended Audience :: Developers
Classifier: Topic :: Software Development :: Build Tools
Classifier: License :: OSI Approved :: MIT License
Classifier: Programming Language :: Python :: 2
Classifier: Programming Language :: Python :: 2.6
Classifier: Programming Language :: Python :: 2.7
Classifier: Programming Language :: Python :: 3
Classifier: Programming Language :: Python :: 3.2
Classifier: Programming Language :: Python :: 3.3
Classifier: Programming Language :: Python :: 3.4
